LICENSE
asyncio_queue_rotation/__init__.py
asyncio_queue_rotation/rotation_queue.py
asyncio_queue_rotation-0.1.0.dist-info/LICENSE
asyncio_queue_rotation-0.1.0.dist-info/WHEEL
asyncio_queue_rotation-0.1.0.dist-info/METADATA
asyncio_queue_rotation-0.1.0.dist-info/RECORD
