Metadata-Version: 2.1
Name: asyncio-queue-rotation
Version: 0.1.0
Summary: 
Home-page: https://github.com/und3v3l0p3d/asyncio-rotation
License: MIT
Keywords: asyncio,queue,rotation
Author: und3v3l0p3d
Author-email: prohibitme@phygitalism.com
Requires-Python: >=3.9,<4.0
Classifier: Framework :: AsyncIO
Classifier: License :: OSI Approved :: MIT License
Classifier: Operating System :: OS Independent
Classifier: Programming Language :: Python :: 3
Classifier: Programming Language :: Python :: 3.9
Project-URL: Repository, https://github.com/und3v3l0p3d/asyncio-rotation
